{
    "sourceFile": "app/dashboard/page.tsx",
    "activeCommit": 0,
    "commits": [
        {
            "activePatchIndex": 0,
            "patches": [
                {
                    "date": 1764506608306,
                    "content": "Index: \n===================================================================\n--- \n+++ \n"
                }
            ],
            "date": 1764506608306,
            "name": "Commit-0",
            "content": "import { AppSidebar } from \"@/components/navbar/app-sidebar\"\nimport { ChartAreaInteractive } from \"@/components/chart-area-interactive\"\nimport { DataTable } from \"@/components/data-table\"\nimport { SectionCards } from \"@/components/section-cards\"\nimport { SiteHeader } from \"@/components/site-header\"\nimport {\n  SidebarInset,\n  SidebarProvider,\n} from \"@/components/ui/sidebar\"\n\nimport data from \"./data.json\"\n\nexport default function Page() {\n  return (\n    <SidebarProvider\n      style={\n        {\n          \"--sidebar-width\": \"calc(var(--spacing) * 72)\",\n          \"--header-height\": \"calc(var(--spacing) * 12)\",\n        } as React.CSSProperties\n      }\n    >\n      <AppSidebar variant=\"inset\" />\n      <SidebarInset>\n        <SiteHeader />\n        <div className=\"flex flex-1 flex-col\">\n          <div className=\"@container/main flex flex-1 flex-col gap-2\">\n            <div className=\"flex flex-col gap-4 py-4 md:gap-6 md:py-6\">\n              <SectionCards />\n              <div className=\"px-4 lg:px-6\">\n                <ChartAreaInteractive />\n              </div>\n              <DataTable data={data} />\n            </div>\n          </div>\n        </div>\n      </SidebarInset>\n    </SidebarProvider>\n  )\n}\n"
        }
    ]
}